{"files":{"packages/br-masks/dist/cpfMask.d.ts":{"size":56,"mtime_nanos":1784335291405016903,"mode":420,"is_dir":false},"packages/br-masks/dist/index.d.ts":{"size":27,"mtime_nanos":1784335291407584759,"mode":420,"is_dir":false},"packages/br-masks/.turbo/turbo-build.log":{"size":138,"mtime_nanos":1784335291443164331,"mode":420,"is_dir":false},"packages/br-masks/dist/index.js":{"size":27,"mtime_nanos":1784335291405447483,"mode":420,"is_dir":false},"packages/br-masks/dist/cpfMask.js":{"size":191,"mtime_nanos":1784335291402185716,"mode":420,"is_dir":false},"packages/br-masks/dist":{"size":0,"mtime_nanos":0,"mode":0,"is_dir":true}},"order":["packages/br-masks/.turbo/turbo-build.log","packages/br-masks/dist","packages/br-masks/dist/cpfMask.d.ts","packages/br-masks/dist/cpfMask.js","packages/br-masks/dist/index.d.ts","packages/br-masks/dist/index.js"]}